PMKL/KernelFunctions.py
PMKL/Optimization.py
PMKL/PMKL.py
PMKL/Transformation.py
PMKL/__init__.py
pyPMKL/KernelFunctions.py
pyPMKL/Optimization.py
pyPMKL/PMKL.py
pyPMKL/Transformation.py
pyPMKL/__init__.py
PMKLpy-0.1.3.dist-info/LICENSE.txt
PMKLpy-0.1.3.dist-info/METADATA
PMKLpy-0.1.3.dist-info/WHEEL
PMKLpy-0.1.3.dist-info/top_level.txt
PMKLpy-0.1.3.dist-info/RECORD
