Metadata-Version: 2.1
Name: PMKLpy
Version: 0.1.3
Summary: Tessellated Kernels SVM
Home-page: https://github.com/Talitsky/PMKL
Author: AT
Author-email: atalitck@asu.edu
License: MIT
Download-URL: https://pypi.org/project/PMKLpy/
Keywords: Kernel learning,SVM,Multiple Kernel Learning
Platform: UNKNOWN
License-File: LICENSE.txt
Requires-Dist: numpy
Requires-Dist: scikit-learn
Requires-Dist: matplotlib
Requires-Dist: scipy
Requires-Dist: libsvm
